idc_index/__init__.py
idc_index/_version.py
idc_index/_version.pyi
idc_index/cli.py
idc_index/index.py
idc_index/py.typed
idc_index-0.11.7.dist-info/METADATA
idc_index-0.11.7.dist-info/WHEEL
idc_index-0.11.7.dist-info/entry_points.txt
idc_index-0.11.7.dist-info/licenses/LICENSE
idc_index-0.11.7.dist-info/RECORD
