Metadata-Version: 2.4
Name: idc-index
Version: 0.11.7
Summary: Package to query and download data from an index of ImagingDataCommons
Project-URL: Homepage, https://github.com/ImagingDataCommons/idc-index
Project-URL: Bug Tracker, https://github.com/ImagingDataCommons/idc-index/issues
Project-URL: Discussions, https://discourse.canceridc.dev/
Project-URL: Changelog, https://github.com/ImagingDataCommons/idc-index/releases
Author-email: Andrey Fedorov <andrey.fedorov@gmail.com>, Vamsi Thiriveedhi <vthiriveedhi@mgh.harvard.edu>
License: MIT License
License-File: LICENSE
Classifier: Development Status :: 4 - Beta
Classifier: Intended Audience :: Developers
Classifier: Intended Audience :: Science/Research
Classifier: License :: OSI Approved :: MIT License
Classifier: Operating System :: OS Independent
Classifier: Programming Language :: Python
Classifier: Programming Language :: Python :: 3
Classifier: Programming Language :: Python :: 3 :: Only
Classifier: Programming Language :: Python :: 3.10
Classifier: Programming Language :: Python :: 3.11
Classifier: Programming Language :: Python :: 3.12
Classifier: Topic :: Scientific/Engineering
Classifier: Typing :: Typed
Requires-Python: >=3.10
Requires-Dist: click
Requires-Dist: duckdb<=1.2.1,>=0.10.0
Requires-Dist: idc-index-data==23.3.1
Requires-Dist: packaging
Requires-Dist: pandas<=2.2.4
Requires-Dist: platformdirs
Requires-Dist: psutil
Requires-Dist: pyarrow
Requires-Dist: requests
Requires-Dist: s5cmd>=0.3.2
Requires-Dist: tqdm
Provides-Extra: dev
Requires-Dist: pytest-cov>=3; extra == 'dev'
Requires-Dist: pytest>=6; extra == 'dev'
Provides-Extra: docs
Requires-Dist: furo>=2023.08.17; extra == 'docs'
Requires-Dist: myst-parser<5.0,>=0.13; extra == 'docs'
Requires-Dist: sphinx-autodoc-typehints; extra == 'docs'
Requires-Dist: sphinx-click; extra == 'docs'
Requires-Dist: sphinx-copybutton; extra == 'docs'
Requires-Dist: sphinx<8,>=7.0; extra == 'docs'
Requires-Dist: sphinxcontrib-mermaid; extra == 'docs'
Provides-Extra: test
Requires-Dist: pytest-cov>=3; extra == 'test'
Requires-Dist: pytest>=6; extra == 'test'
